loadanim/__init__.py
loadanim/loadanim.py
loadanim-1.0.4.dist-info/LICENSE
loadanim-1.0.4.dist-info/METADATA
loadanim-1.0.4.dist-info/WHEEL
loadanim-1.0.4.dist-info/top_level.txt
loadanim-1.0.4.dist-info/RECORD
