Metadata-Version: 2.1
Name: loadanim
Version: 1.0.4
Summary: Displays cool loading animations to the terminal
Home-page: https://github.com/silas-hw/loading-pkg
Author: Silas Hayes-Williams
Author-email: silas.hayes.williams@gmail.com
License: UNKNOWN
Project-URL: Bug Tracker, https://github.com/silas-hw/loading-pkg/issues
Platform: UNKNOWN
Classifier: Programming Language :: Python :: 3
Classifier: License :: OSI Approved :: MIT License
Classifier: Operating System :: OS Independent
Requires-Python: >=3.6
License-File: LICENSE
